{
  "schemaVersion": 1,
  "id": "buruguru_2023",
  "identifiers": {
    "subscriptionKey": "버넥트_20230717_20230718",
    "normalizedCompany": "버넥트",
    "corpCode": "01605529",
    "stockCode": null,
    "kindCode": null,
    "isin": null
  },
  "company": "버넥트",
  "market": "KOSDAQ",
  "subscriptionStart": "2023-07-17",
  "subscriptionEnd": "2023-07-18",
  "leadManagers": [
    "대신증권"
  ],
  "fundamentals": {
    "offerPrice": 16000,
    "priceBandMin": 11500,
    "priceBandMax": 13600,
    "institutionCompetitionRate": 1824.09,
    "institutionParticipants": null,
    "lockupCommitmentRate": null,
    "floatRate": null,
    "marketCapKrw": null,
    "publicAllocationShares": null
  },
  "outcome": null,
  "snapshots": [
    {
      "capturedAt": "2023-07-18T16:00:00+09:00",
      "source": "public_ipo_backfill",
      "sourceUrl": "https://finfreedom.tistory.com",
      "brokers": [
        {
          "name": "통합",
          "offeredShares": 0,
          "subscribedShares": 0,
          "offerPrice": null,
          "depositRate": null,
          "feeKrw": null,
          "competitionRate": 1311.65,
          "equalCompetitionRate": null,
          "proportionalCompetitionRate": null,
          "equalAllocationShares": null,
          "proportionalAllocationShares": null,
          "applicationCount": null
        }
      ],
      "aggregate": {
        "offeredShares": 0,
        "subscribedShares": 0,
        "competitionRate": 1311.65
      }
    },
    {
      "capturedAt": "2026-04-27T00:48:52.971808",
      "source": "estimated_broker_rate_only",
      "sourceUrl": "https://finfreedom.tistory.com",
      "brokers": [
        {
          "name": "대신증권",
          "offeredShares": 0,
          "subscribedShares": 0,
          "offerPrice": 16000,
          "depositRate": null,
          "feeKrw": null,
          "competitionRate": 1311.65,
          "equalCompetitionRate": null,
          "proportionalCompetitionRate": 1311.65,
          "equalAllocationShares": null,
          "proportionalAllocationShares": null,
          "applicationCount": null
        }
      ],
      "aggregate": {
        "offeredShares": 0,
        "subscribedShares": 0,
        "competitionRate": 1311.65
      }
    }
  ],
  "analysis": {
    "methodVersion": "ipo-score-v4",
    "score": {
      "overall": 39,
      "grade": "D",
      "confidence": 0.95,
      "factors": {
        "competition": 13,
        "institutionDemand": 24,
        "lockupCommitment": 0,
        "floatRate": 0,
        "pricing": 2,
        "market": 0,
        "leadManagers": 0,
        "recency": 0,
        "dataCompleteness": 0
      }
    },
    "expectedReturn": {
      "expectedListingGainRate": 0.2849,
      "bearCaseListingGainRate": 0.0649,
      "baseCaseListingGainRate": 0.2849,
      "bullCaseListingGainRate": 0.6349,
      "expectedAllocatedShares": {
        "minimumSubscription": 0.008,
        "oneMillionKrw": 0.048,
        "fiveMillionKrw": 0.238
      },
      "expectedProfitKrw": {
        "minimumSubscription": -1965,
        "oneMillionKrw": -1783,
        "fiveMillionKrw": -914
      },
      "assumptions": {
        "offerPrice": 16000,
        "competitionRate": 1311.65,
        "feeKrw": 2000,
        "method": "ipo_score_v2_general_rule_based"
      }
    },
    "decision": {
      "level": "caution",
      "label": "주의",
      "reasons": [
        "최근 확인된 일반청약 경쟁률은 1311.65대 1입니다."
      ],
      "warnings": [
        "경쟁률이 높아 실제 배정 수량은 매우 작을 수 있습니다.",
        "본 지표는 투자 권유가 아니라 공개 데이터 기반 참고값입니다."
      ]
    },
    "brokerScores": [
      {
        "broker": "대신증권",
        "equalScore": 30,
        "proportionalScore": 10,
        "expectedEqualShares": null,
        "estimatedDepositForOneProportionalShare": 10493200,
        "feeKrw": null,
        "dataQuality": "partial"
      }
    ],
    "inputs": {
      "latestCompetitionRate": 1311.65,
      "snapshotCount": 2,
      "leadManagerCount": 1,
      "market": "KOSDAQ",
      "hasOfferPrice": true,
      "institutionCompetitionRate": 1824.09,
      "lockupCommitmentRate": null,
      "floatRate": null,
      "hasOutcome": false
    },
    "disclaimer": "공개 데이터 기반 참고 지표이며 투자 권유가 아닙니다."
  }
}
