{
  "schemaVersion": 1,
  "id": "ck_solution_2025",
  "identifiers": {
    "subscriptionKey": "씨케이솔루션_20250304_20250305",
    "normalizedCompany": "씨케이솔루션",
    "corpCode": "01854064",
    "stockCode": null,
    "kindCode": null,
    "isin": null
  },
  "company": "씨케이솔루션",
  "market": "KOSPI",
  "subscriptionStart": "2025-03-04",
  "subscriptionEnd": "2025-03-05",
  "leadManagers": [
    "NH투자증권"
  ],
  "fundamentals": {
    "offerPrice": 15000,
    "priceBandMin": 13500,
    "priceBandMax": 15000,
    "institutionCompetitionRate": 1020.35,
    "institutionParticipants": null,
    "lockupCommitmentRate": null,
    "floatRate": null,
    "marketCapKrw": null,
    "publicAllocationShares": null
  },
  "outcome": null,
  "snapshots": [
    {
      "capturedAt": "2025-03-05T16:00:00+09:00",
      "source": "public_monthly_ipo_schedule",
      "sourceUrl": "https://honda31.tistory.com/290",
      "brokers": [
        {
          "name": "통합",
          "offeredShares": 0,
          "subscribedShares": 0,
          "offerPrice": null,
          "depositRate": null,
          "feeKrw": null,
          "competitionRate": 1320.68,
          "equalCompetitionRate": null,
          "proportionalCompetitionRate": null,
          "equalAllocationShares": null,
          "proportionalAllocationShares": null,
          "applicationCount": null
        }
      ],
      "aggregate": {
        "offeredShares": 0,
        "subscribedShares": 0,
        "competitionRate": 1320.68
      }
    },
    {
      "capturedAt": "2026-04-26T17:16:29.422449",
      "source": "estimated_broker_rate_only",
      "sourceUrl": "https://honda31.tistory.com/290",
      "brokers": [
        {
          "name": "NH투자증권",
          "offeredShares": 0,
          "subscribedShares": 0,
          "offerPrice": 15000,
          "depositRate": null,
          "feeKrw": null,
          "competitionRate": 1320.68,
          "equalCompetitionRate": null,
          "proportionalCompetitionRate": 1320.68,
          "equalAllocationShares": null,
          "proportionalAllocationShares": null,
          "applicationCount": null
        }
      ],
      "aggregate": {
        "offeredShares": 0,
        "subscribedShares": 0,
        "competitionRate": 1320.68
      }
    }
  ],
  "analysis": {
    "methodVersion": "ipo-score-v4",
    "score": {
      "overall": 54,
      "grade": "C",
      "confidence": 0.95,
      "factors": {
        "competition": 13,
        "institutionDemand": 20,
        "lockupCommitment": 0,
        "floatRate": 0,
        "pricing": 5,
        "market": 6,
        "leadManagers": 3,
        "recency": 0,
        "dataCompleteness": 7
      }
    },
    "expectedReturn": {
      "expectedListingGainRate": 0.4323,
      "bearCaseListingGainRate": 0.2123,
      "baseCaseListingGainRate": 0.4323,
      "bullCaseListingGainRate": 0.7823,
      "expectedAllocatedShares": {
        "minimumSubscription": 0.008,
        "oneMillionKrw": 0.05,
        "fiveMillionKrw": 0.252
      },
      "expectedProfitKrw": {
        "minimumSubscription": -1951,
        "oneMillionKrw": -1673,
        "fiveMillionKrw": -363
      },
      "assumptions": {
        "offerPrice": 15000,
        "competitionRate": 1320.68,
        "feeKrw": 2000,
        "method": "ipo_score_v2_general_rule_based"
      }
    },
    "decision": {
      "level": "neutral",
      "label": "중립",
      "reasons": [
        "최근 확인된 일반청약 경쟁률은 1320.68대 1입니다."
      ],
      "warnings": [
        "경쟁률이 높아 실제 배정 수량은 매우 작을 수 있습니다.",
        "본 지표는 투자 권유가 아니라 공개 데이터 기반 참고값입니다."
      ]
    },
    "brokerScores": [
      {
        "broker": "NH투자증권",
        "equalScore": 30,
        "proportionalScore": 10,
        "expectedEqualShares": null,
        "estimatedDepositForOneProportionalShare": 9905100,
        "feeKrw": null,
        "dataQuality": "partial"
      }
    ],
    "inputs": {
      "latestCompetitionRate": 1320.68,
      "snapshotCount": 2,
      "leadManagerCount": 1,
      "market": "KOSPI",
      "hasOfferPrice": true,
      "institutionCompetitionRate": 1020.35,
      "lockupCommitmentRate": null,
      "floatRate": null,
      "hasOutcome": false
    },
    "disclaimer": "공개 데이터 기반 참고 지표이며 투자 권유가 아닙니다."
  }
}
