{
  "schemaVersion": 1,
  "id": "inix_2024",
  "identifiers": {
    "subscriptionKey": "이닉스_20240123_20240124",
    "normalizedCompany": "이닉스",
    "corpCode": "00164779",
    "stockCode": null,
    "kindCode": null,
    "isin": null
  },
  "company": "이닉스",
  "market": "KOSDAQ",
  "subscriptionStart": "2024-01-23",
  "subscriptionEnd": "2024-01-24",
  "leadManagers": [
    "삼성증권"
  ],
  "fundamentals": {
    "offerPrice": 14000,
    "priceBandMin": 9200,
    "priceBandMax": 11000,
    "institutionCompetitionRate": 670.6,
    "institutionParticipants": null,
    "lockupCommitmentRate": null,
    "floatRate": null,
    "marketCapKrw": null,
    "publicAllocationShares": null
  },
  "outcome": {
    "listingDate": "2024-02-01",
    "openReturnRate": null,
    "highReturnRate": null,
    "closeReturnRate": 1.65,
    "sourceUrl": "https://www.fnnews.com/news/202402011539341900"
  },
  "snapshots": [
    {
      "capturedAt": "2024-01-24T17:30:00+09:00",
      "source": "article_final",
      "sourceUrl": "https://www.fnnews.com/news/202402011539341900",
      "brokers": [
        {
          "name": "통합",
          "offeredShares": 0,
          "subscribedShares": 0,
          "offerPrice": null,
          "depositRate": null,
          "feeKrw": null,
          "competitionRate": 1997.39,
          "equalCompetitionRate": null,
          "proportionalCompetitionRate": null,
          "equalAllocationShares": null,
          "proportionalAllocationShares": null,
          "applicationCount": null
        }
      ],
      "aggregate": {
        "offeredShares": 0,
        "subscribedShares": 0,
        "competitionRate": 1997.39
      }
    },
    {
      "capturedAt": "2026-04-23T09:53:45.093668",
      "source": "estimated_broker_rate_only",
      "sourceUrl": "https://www.fnnews.com/news/202402011539341900",
      "brokers": [
        {
          "name": "삼성증권",
          "offeredShares": 0,
          "subscribedShares": 0,
          "offerPrice": 14000,
          "depositRate": null,
          "feeKrw": null,
          "competitionRate": 1997.39,
          "equalCompetitionRate": null,
          "proportionalCompetitionRate": 1997.39,
          "equalAllocationShares": null,
          "proportionalAllocationShares": null,
          "applicationCount": null
        }
      ],
      "aggregate": {
        "offeredShares": 0,
        "subscribedShares": 0,
        "competitionRate": 1997.39
      }
    },
    {
      "capturedAt": "2026-04-23T09:53:45.093668",
      "source": "estimated_broker_rate_only",
      "sourceUrl": "https://www.fnnews.com/news/202402011539341900",
      "brokers": [
        {
          "name": "삼성증권",
          "offeredShares": 0,
          "subscribedShares": 0,
          "offerPrice": 14000,
          "depositRate": null,
          "feeKrw": null,
          "competitionRate": 1997.39,
          "equalCompetitionRate": null,
          "proportionalCompetitionRate": 1997.39,
          "equalAllocationShares": null,
          "proportionalAllocationShares": null,
          "applicationCount": null
        }
      ],
      "aggregate": {
        "offeredShares": 0,
        "subscribedShares": 0,
        "competitionRate": 1997.39
      }
    }
  ],
  "analysis": {
    "methodVersion": "ipo-score-v2",
    "score": {
      "overall": 41,
      "grade": "D",
      "confidence": 0.95,
      "factors": {
        "competition": 16,
        "institutionDemand": 8,
        "lockupCommitment": 0,
        "floatRate": 0,
        "pricing": 2,
        "market": 5,
        "leadManagers": 3,
        "recency": 0,
        "dataCompleteness": 7
      }
    },
    "expectedReturn": {
      "expectedListingGainRate": 0.3046,
      "bearCaseListingGainRate": 0.0846,
      "baseCaseListingGainRate": 0.3046,
      "bullCaseListingGainRate": 0.6546,
      "expectedAllocatedShares": {
        "minimumSubscription": 0.005,
        "oneMillionKrw": 0.036,
        "fiveMillionKrw": 0.179
      },
      "expectedProfitKrw": {
        "minimumSubscription": -1979,
        "oneMillionKrw": -1848,
        "fiveMillionKrw": -1238
      },
      "assumptions": {
        "offerPrice": 14000,
        "competitionRate": 1997.39,
        "feeKrw": 2000,
        "method": "rule_based_v1_low_confidence"
      }
    },
    "decision": {
      "level": "caution",
      "label": "주의",
      "reasons": [
        "최근 확인된 일반청약 경쟁률은 1997.39대 1입니다."
      ],
      "warnings": [
        "경쟁률이 높아 실제 배정 수량은 매우 작을 수 있습니다.",
        "본 지표는 투자 권유가 아니라 공개 데이터 기반 참고값입니다."
      ]
    },
    "brokerScores": [
      {
        "broker": "삼성증권",
        "equalScore": 30,
        "proportionalScore": 7,
        "expectedEqualShares": null,
        "estimatedDepositForOneProportionalShare": 13981730,
        "feeKrw": null,
        "dataQuality": "partial"
      }
    ],
    "inputs": {
      "latestCompetitionRate": 1997.39,
      "snapshotCount": 3,
      "leadManagerCount": 1,
      "market": "KOSDAQ",
      "hasOfferPrice": true,
      "institutionCompetitionRate": 670.6,
      "lockupCommitmentRate": null,
      "floatRate": null,
      "hasOutcome": true
    },
    "disclaimer": "공개 데이터 기반 참고 지표이며 투자 권유가 아닙니다."
  }
}
