{
  "schemaVersion": 1,
  "id": "intocell_2025",
  "identifiers": {
    "subscriptionKey": "인투셀_20250513_20250514",
    "normalizedCompany": "인투셀",
    "corpCode": "01374443",
    "stockCode": null,
    "kindCode": null,
    "isin": null
  },
  "company": "인투셀",
  "market": "KOSDAQ",
  "subscriptionStart": "2025-05-13",
  "subscriptionEnd": "2025-05-14",
  "leadManagers": [
    "미래에셋증권"
  ],
  "fundamentals": {
    "offerPrice": 17000,
    "priceBandMin": 12500,
    "priceBandMax": 17000,
    "institutionCompetitionRate": 1151.5,
    "institutionParticipants": null,
    "lockupCommitmentRate": null,
    "floatRate": null,
    "marketCapKrw": null,
    "publicAllocationShares": null
  },
  "outcome": null,
  "snapshots": [
    {
      "capturedAt": "2025-05-14T16:00:00+09:00",
      "source": "public_monthly_ipo_schedule",
      "sourceUrl": "https://honda31.tistory.com/298",
      "brokers": [
        {
          "name": "통합",
          "offeredShares": 0,
          "subscribedShares": 0,
          "offerPrice": null,
          "depositRate": null,
          "feeKrw": null,
          "competitionRate": 2268.86,
          "equalCompetitionRate": null,
          "proportionalCompetitionRate": null,
          "equalAllocationShares": null,
          "proportionalAllocationShares": null,
          "applicationCount": null
        }
      ],
      "aggregate": {
        "offeredShares": 0,
        "subscribedShares": 0,
        "competitionRate": 2268.86
      }
    },
    {
      "capturedAt": "2026-04-27T01:00:38.230703",
      "source": "estimated_broker_rate_only",
      "sourceUrl": "https://honda31.tistory.com/298",
      "brokers": [
        {
          "name": "미래에셋증권",
          "offeredShares": 0,
          "subscribedShares": 0,
          "offerPrice": 17000,
          "depositRate": null,
          "feeKrw": null,
          "competitionRate": 2268.86,
          "equalCompetitionRate": null,
          "proportionalCompetitionRate": 2268.86,
          "equalAllocationShares": null,
          "proportionalAllocationShares": null,
          "applicationCount": null
        }
      ],
      "aggregate": {
        "offeredShares": 0,
        "subscribedShares": 0,
        "competitionRate": 2268.86
      }
    }
  ],
  "analysis": {
    "methodVersion": "ipo-score-v4",
    "score": {
      "overall": 51,
      "grade": "C+",
      "confidence": 0.95,
      "factors": {
        "competition": 16,
        "institutionDemand": 20,
        "demandStrength": 4,
        "lockupCommitment": 0,
        "floatRate": 0,
        "pricing": 6
      }
    },
    "expectedReturn": {
      "expectedListingGainRate": 0.4028,
      "bearCaseListingGainRate": 0.1828,
      "baseCaseListingGainRate": 0.4028,
      "bullCaseListingGainRate": 0.7528,
      "expectedAllocatedShares": {
        "minimumSubscription": 0.004,
        "oneMillionKrw": 0.026,
        "fiveMillionKrw": 0.13
      },
      "expectedProfitKrw": {
        "minimumSubscription": -1970,
        "oneMillionKrw": -1822,
        "fiveMillionKrw": -1112
      },
      "assumptions": {
        "offerPrice": 17000,
        "competitionRate": 2268.86,
        "feeKrw": 2000,
        "method": "ipo_score_v2_general_rule_based"
      }
    },
    "decision": {
      "level": "caution",
      "label": "주의",
      "reasons": [
        "최근 확인된 일반청약 경쟁률은 2268.86대 1입니다."
      ],
      "warnings": [
        "경쟁률이 높아 실제 배정 수량은 매우 작을 수 있습니다.",
        "본 지표는 투자 권유가 아니라 공개 데이터 기반 참고값입니다."
      ]
    },
    "brokerScores": [
      {
        "broker": "미래에셋증권",
        "equalScore": 30,
        "proportionalScore": 5,
        "expectedEqualShares": null,
        "estimatedDepositForOneProportionalShare": 19285310,
        "feeKrw": null,
        "dataQuality": "partial"
      }
    ],
    "inputs": {
      "latestCompetitionRate": 2268.86,
      "snapshotCount": 2,
      "leadManagerCount": 1,
      "market": "KOSDAQ",
      "hasOfferPrice": true,
      "institutionCompetitionRate": 1151.5,
      "lockupCommitmentRate": null,
      "floatRate": null,
      "hasOutcome": false
    },
    "disclaimer": "공개 데이터 기반 참고 지표이며 투자 권유가 아닙니다."
  }
}
